nsp2visasim/__init__.py
nsp2visasim/sim_led.json.gz
nsp2visasim/sim_pv.json.gz
nsp2visasim/sim_pv_bright.json.gz
nsp2visasim/sim_pyvisa.py
nsp2visasim-1.4.1.post2.dist-info/METADATA
nsp2visasim-1.4.1.post2.dist-info/WHEEL
nsp2visasim-1.4.1.post2.dist-info/RECORD
