Metadata-Version: 2.1
Name: nsp2visasim
Version: 1.4.1.post2
Summary: A simulated device for measuring LED characteristics.
License: MIT
Author: David Fokkema
Author-email: davidfokkema@icloud.com
Requires-Python: >=3.8,<4.0
Classifier: License :: OSI Approved :: MIT License
Classifier: Programming Language :: Python :: 3
Classifier: Programming Language :: Python :: 3.8
Classifier: Programming Language :: Python :: 3.9
Classifier: Programming Language :: Python :: 3.10
Classifier: Programming Language :: Python :: 3.11
Classifier: Programming Language :: Python :: 3.12
Classifier: Programming Language :: Python :: 3.13
Requires-Dist: PyVISA (>=1.11.3,<2.0.0)
